jupyterhub_ai_gateway/__init__.py
jupyterhub_ai_gateway/app.py
jupyterhub_ai_gateway/cli.py
jupyterhub_ai_gateway/client.py
jupyterhub_ai_gateway/constants.py
jupyterhub_ai_gateway/models.py
jupyterhub_ai_gateway/security.py
jupyterhub_ai_gateway/settings.py
jupyterhub_ai_gateway/utils.py
jupyterhub_ai_gateway/metrics/__init__.py
jupyterhub_ai_gateway/metrics/metrics.py
jupyterhub_ai_gateway/metrics/middleware.py
jupyterhub_ai_gateway/routers/__init__.py
jupyterhub_ai_gateway/routers/gateway.py
jupyterhub_ai_gateway/routers/service.py
jupyterhub_ai_gateway-2.0.1.dist-info/LICENSE.md
jupyterhub_ai_gateway-2.0.1.dist-info/METADATA
jupyterhub_ai_gateway-2.0.1.dist-info/WHEEL
jupyterhub_ai_gateway-2.0.1.dist-info/entry_points.txt
jupyterhub_ai_gateway-2.0.1.dist-info/top_level.txt
jupyterhub_ai_gateway-2.0.1.dist-info/RECORD
