Metadata-Version: 2.1
Name: jupyterhub-ai-gateway
Version: 2.0.1
Summary: AI gateway service for JupyterHub.
Author-email: Danilo Peixoto Ferreira <danilopeixoto@outlook.com>
License: Copyright (c) 2024, JupyterHub AI Gateway Developers. All rights reserved.
Project-URL: Homepage, https://jupyterhub-ai-gateway.readthedocs.io
Project-URL: Documentation, https://jupyterhub-ai-gateway.readthedocs.io
Project-URL: Repository, https://github.com/danilopeixoto/jupyterhub-ai-gateway
Project-URL: Issues, https://github.com/danilopeixoto/jupyterhub-ai-gateway/issues
Project-URL: Changelog, https://jupyterhub-ai-gateway.readthedocs.io/en/stable/changelog.html
Keywords: ai,gateway,jupyterhub,mlflow,service
Classifier: Programming Language :: Python
Classifier: Programming Language :: Python :: 3
Classifier: Programming Language :: Python :: 3.10
Classifier: License :: OSI Approved :: MIT License
Requires-Python: >=3.10.0
License-File: LICENSE.md
Requires-Dist: fastapi
Requires-Dist: python-multipart
Requires-Dist: uvicorn[standard]
Requires-Dist: pydantic
Requires-Dist: pydantic-settings
Requires-Dist: httpx
Requires-Dist: mlflow[genai]
Requires-Dist: prometheus-client
Provides-Extra: development
Requires-Dist: mypy ; extra == 'development'
Requires-Dist: isort ; extra == 'development'
Requires-Dist: black ; extra == 'development'
Requires-Dist: pylint ; extra == 'development'
Requires-Dist: pre-commit ; extra == 'development'
Requires-Dist: pytest ; extra == 'development'
Requires-Dist: sphinx ; extra == 'development'
Requires-Dist: sphinx-autobuild ; extra == 'development'
Requires-Dist: sphinx-book-theme ; extra == 'development'
Requires-Dist: sphinx-favicon ; extra == 'development'
Requires-Dist: myst-parser ; extra == 'development'
Requires-Dist: build ; extra == 'development'
Requires-Dist: twine ; extra == 'development'
